{"cameraMode":{"drawMode":0,"name":"Shaded","section":"Shading Mode"},"sceneLighting":true,"audioPlay":false,"sceneViewState":{"m_AlwaysRefresh":false,"showFog":true,"showSkybox":true,"showFlares":true,"showImageEffects":true,"showParticleSystems":true,"showVisualEffectGraphs":true,"m_FxEnabled":true},"in2DMode":false,"pivot":{"x":0.008489370346069336,"y":-0.888071596622467,"z":-0.7384207248687744},"rotation":{"x":-0.18950781226158143,"y":0.7740278244018555,"z":-0.2718958854675293,"w":-0.539484977722168},"size":831.2632446289063,"orthographic":false}